[
    {
        "_id": "tienganh3tap1",
        "name": "Tiếng Anh 3 Tập 1"
    },
    {
        "_id": "tienganh3tap2",
        "name": "Tiếng Anh 3 Tập 2"
    },
    {
        "_id": "tienganh4tap1",
        "name": "Tiếng Anh 4 Tập 1"
    },
    {
        "_id": "tienganh4tap2",
        "name": "Tiếng Anh 4 Tập 2"
    },
    {
        "_id": "tienganh5tap1",
        "name": "Tiếng Anh 5 Tập 1"
    },
    {
        "_id": "tienganh5tap2",
        "name": "Tiếng Anh 5 Tập 2"
    },
    {
        "_id": "tienganh6tap1",
        "name": "Tiếng Anh 6 Tập 1 (2021) - Global Success"
    },
    {
        "_id": "tienganh6tap2",
        "name": "Tiếng Anh 6 Tập 2 (2021) - Global Success"
    },
    {
        "_id": "tienganh7tap1",
        "name": "Tiếng Anh 7 Tập 1"
    },
    {
        "_id": "tienganh7tap2",
        "name": "Tiếng Anh 7 Tập 2"
    },
    {
        "_id": "tienganh8tap1",
        "name": "Tiếng Anh 8 Tập 1"
    },
    {
        "_id": "tienganh8tap2",
        "name": "Tiếng Anh 8 Tập 2"
    },
    {
        "_id": "tienganh9tap1",
        "name": "Tiếng Anh 9 Tập 1"
    },
    {
        "_id": "tienganh9tap2",
        "name": "Tiếng Anh 9 Tập 2"
    },
    {
        "_id": "tienganh10tap1",
        "name": "Tiếng Anh 10 Tập 1"
    },
    {
        "_id": "tienganh10tap2",
        "name": "Tiếng Anh 10 Tập 2"
    },
    {
        "_id": "tienganh11tap1",
        "name": "Tiếng Anh 11 Tập 1"
    },
    {
        "_id": "tienganh11tap2",
        "name": "Tiếng Anh 11 Tập 2"
    },
    {
        "_id": "tienganh12tap1",
        "name": "Tiếng Anh 12 Tập 1"
    },
    {
        "_id": "tienganh12tap2",
        "name": "Tiếng Anh 12 Tập 2"
    },
    {
        "_id": "tienganh12020",
        "name": "Tiếng Anh 1 2020 - Global Success"
    },
    {
        "_id": "tienganh2ctgdpt2018",
        "name": "Tiếng Anh 2 (CT GDPT 2018) - Global Success"
    },
    {
        "_id": "tienganh3tap1demo",
        "name": "Tiếng Anh 3 Tập 1 Demo"
    },
    {
        "_id": "tienganh7tap1demo",
        "name": "Tiếng Anh 7 Tập 1 Demo"
    },
    {
        "_id": "tienganh10tap2demo",
        "name": "Tiếng Anh 10 Tập 2 Demo"
    }
]